{
  "format": "kc-mission-v1",
  "exportedAt": "2026-02-27T18:28:56.223Z",
  "exportedBy": "cncf-mission-generator",
  "consoleVersion": "auto-generated",
  "mission": {
    "title": "keycloak: Manage Organization Roles",
    "description": "Closes #40585",
    "type": "troubleshoot",
    "status": "completed",
    "resolution": {
      "summary": "@ssilvert I would actually pay for this feature to be merged.",
      "steps": [
        "Review the issue discussion for context",
        "Apply the fix from the linked pull request"
      ]
    }
  },
  "metadata": {
    "tags": [
      "keycloak",
      "incubating",
      "security"
    ],
    "category": "security",
    "cncfProjects": [
      "keycloak"
    ],
    "targetResourceKinds": [
      "Role"
    ],
    "difficulty": "beginner",
    "sourceIssue": "https://github.com/keycloak/keycloak/pull/40586",
    "sourceRepo": "keycloak/keycloak",
    "reactions": 16,
    "comments": 5
  },
  "security": {
    "scannedAt": "2026-02-27T18:28:56.223Z",
    "scannerVersion": "cncf-gen-1.0.0",
    "sanitized": true,
    "findings": []
  }
}
