{
  "format": "kc-mission-v1",
  "exportedAt": "2026-02-27T17:44:30.428Z",
  "exportedBy": "cncf-mission-generator",
  "consoleVersion": "auto-generated",
  "mission": {
    "title": "keycloak: Use email verification instead of executing action for `send-verify-email` endpoint",
    "description": "Closes #15190\n\nAdd support for `send-verify-email` endpoint to use the `email-verification.ftl` instead of `executeActions.ftl`\n\nAlso introduce a new parameter `lifespan` to be able to override the default lifespan value (12 hours)",
    "type": "troubleshoot",
    "status": "completed",
    "resolution": {
      "summary": "Can we get a bump on this.  This will fix an issue we are having",
      "steps": [
        "Review the issue discussion for context",
        "Apply the fix from the linked pull request"
      ],
      "codeSnippets": [
        "/realms/{realm}/login-actions/action-token?key={token}"
      ]
    }
  },
  "metadata": {
    "tags": [
      "keycloak",
      "incubating",
      "security",
      "flaky-test"
    ],
    "category": "security",
    "cncfProjects": [
      "keycloak"
    ],
    "targetResourceKinds": [],
    "difficulty": "intermediate",
    "sourceIssue": "https://github.com/keycloak/keycloak/pull/23303",
    "sourceRepo": "keycloak/keycloak",
    "reactions": 10,
    "comments": 11
  },
  "security": {
    "scannedAt": "2026-02-27T17:44:30.428Z",
    "scannerVersion": "cncf-gen-1.0.0",
    "sanitized": true,
    "findings": []
  }
}
