{
  "format": "kc-mission-v1",
  "exportedAt": "2026-02-27T18:32:19.663Z",
  "exportedBy": "cncf-mission-generator",
  "consoleVersion": "auto-generated",
  "mission": {
    "title": "thanos: receive: Enable exemplars ingestion and querying",
    "description": "* [x] I added CHANGELOG entry for this change.\n* [ ] Change is not relevant to the end user.\n\n## Changes\n- Enable exemplar ingestion in Receive\n- Add exemplars API implementation for TSDB and MultiTSDB\n- Expose exemplars gRPC API from Receive\n\nFixes #4235 \n\n## Verification\n- Local testing, modified some existing tests for ingestion. Need to add E2E tests.",
    "type": "troubleshoot",
    "status": "completed",
    "resolution": {
      "summary": "Let's rebase and merge this",
      "steps": [
        "Review the issue discussion for context",
        "Apply the fix from the linked pull request"
      ]
    }
  },
  "metadata": {
    "tags": [
      "thanos",
      "incubating",
      "observability"
    ],
    "category": "observability",
    "cncfProjects": [
      "thanos"
    ],
    "targetResourceKinds": [],
    "difficulty": "beginner",
    "sourceIssue": "https://github.com/thanos-io/thanos/pull/4292",
    "sourceRepo": "thanos-io/thanos",
    "reactions": 6,
    "comments": 1
  },
  "security": {
    "scannedAt": "2026-02-27T18:32:19.663Z",
    "scannerVersion": "cncf-gen-1.0.0",
    "sanitized": true,
    "findings": []
  }
}
